victorstest/cli/cli.py
victorstest-0.1.0.dist-info/LICENSE
victorstest-0.1.0.dist-info/METADATA
victorstest-0.1.0.dist-info/WHEEL
victorstest-0.1.0.dist-info/entry_points.txt
victorstest-0.1.0.dist-info/top_level.txt
victorstest-0.1.0.dist-info/RECORD
