Metadata-Version: 2.1
Name: victorstest
Version: 0.1.0
Summary: victors test project
Author-email: victorscomma <victorscomma@gmail.com>
License: Creative Commons Legal Code
Keywords: victorstest
License-File: LICENSE
Requires-Dist: numpy
Requires-Dist: boto3
